bugmenot/__init__.py
bugmenot/__main__.py
bugmenot/core.py
bugmenot/utils.py
bugmenot-0.1.0.dist-info/LICENSE
bugmenot-0.1.0.dist-info/METADATA
bugmenot-0.1.0.dist-info/WHEEL
bugmenot-0.1.0.dist-info/entry_points.txt
bugmenot-0.1.0.dist-info/top_level.txt
bugmenot-0.1.0.dist-info/RECORD
