Metadata-Version: 2.1
Name: bugmenot
Version: 0.1.0
Summary: Unofficial Python package to retrieve credentials from BugMeNot.com
Home-page: http://github.com/ptrstn/bugmenot
Author: Peter Stein
License: Unlicense
Platform: UNKNOWN
Classifier: Programming Language :: Python :: 3
Classifier: License :: Public Domain
Classifier: Operating System :: OS Independent
Requires-Python: >=3.6
Requires-Dist: requests
Requires-Dist: beautifulsoup4
